<?xml version="1.0" encoding="UTF-8"?>
<?xml-stylesheet href="CoreNLP-to-HTML.xsl" type="text/xsl"?>
<root>
  <document>
    <sentences>
      <sentence id="1">
        <tokens>
          <token id="1">
            <word>A</word>
            <lemma>a</lemma>
            <CharacterOffsetBegin>0</CharacterOffsetBegin>
            <CharacterOffsetEnd>1</CharacterOffsetEnd>
            <POS>DT</POS>
            <NER>DURATION</NER>
            <NormalizedNER>PXY</NormalizedNER>
            <Speaker>PER0</Speaker>
            <Timex tid="t1" type="DURATION">PXY</Timex>
          </token>
          <token id="2">
            <word>few</word>
            <lemma>few</lemma>
            <CharacterOffsetBegin>2</CharacterOffsetBegin>
            <CharacterOffsetEnd>5</CharacterOffsetEnd>
            <POS>JJ</POS>
            <NER>DURATION</NER>
            <NormalizedNER>PXY</NormalizedNER>
            <Speaker>PER0</Speaker>
            <Timex tid="t1" type="DURATION">PXY</Timex>
          </token>
          <token id="3">
            <word>years</word>
            <lemma>year</lemma>
            <CharacterOffsetBegin>6</CharacterOffsetBegin>
            <CharacterOffsetEnd>11</CharacterOffsetEnd>
            <POS>NNS</POS>
            <NER>DURATION</NER>
            <NormalizedNER>PXY</NormalizedNER>
            <Speaker>PER0</Speaker>
            <Timex tid="t1" type="DURATION">PXY</Timex>
          </token>
          <token id="4">
            <word>after</word>
            <lemma>after</lemma>
            <CharacterOffsetBegin>12</CharacterOffsetBegin>
            <CharacterOffsetEnd>17</CharacterOffsetEnd>
            <POS>IN</POS>
            <NER>O</NER>
            <Speaker>PER0</Speaker>
          </token>
          <token id="5">
            <word>they</word>
            <lemma>they</lemma>
            <CharacterOffsetBegin>18</CharacterOffsetBegin>
            <CharacterOffsetEnd>22</CharacterOffsetEnd>
            <POS>PRP</POS>
            <NER>O</NER>
            <Speaker>PER0</Speaker>
          </token>
          <token id="6">
            <word>first</word>
            <lemma>first</lemma>
            <CharacterOffsetBegin>23</CharacterOffsetBegin>
            <CharacterOffsetEnd>28</CharacterOffsetEnd>
            <POS>RB</POS>
            <NER>ORDINAL</NER>
            <NormalizedNER>1.0</NormalizedNER>
            <Speaker>PER0</Speaker>
          </token>
          <token id="7">
            <word>met</word>
            <lemma>meet</lemma>
            <CharacterOffsetBegin>29</CharacterOffsetBegin>
            <CharacterOffsetEnd>32</CharacterOffsetEnd>
            <POS>VBD</POS>
            <NER>O</NER>
            <Speaker>PER0</Speaker>
          </token>
          <token id="8">
            <word>,</word>
            <lemma>,</lemma>
            <CharacterOffsetBegin>32</CharacterOffsetBegin>
            <CharacterOffsetEnd>33</CharacterOffsetEnd>
            <POS>,</POS>
            <NER>O</NER>
            <Speaker>PER0</Speaker>
          </token>
          <token id="9">
            <word>Naomi</word>
            <lemma>Naomi</lemma>
            <CharacterOffsetBegin>34</CharacterOffsetBegin>
            <CharacterOffsetEnd>39</CharacterOffsetEnd>
            <POS>NNP</POS>
            <NER>PERSON</NER>
            <Speaker>PER0</Speaker>
          </token>
          <token id="10">
            <word>Armitage</word>
            <lemma>Armitage</lemma>
            <CharacterOffsetBegin>40</CharacterOffsetBegin>
            <CharacterOffsetEnd>48</CharacterOffsetEnd>
            <POS>NNP</POS>
            <NER>PERSON</NER>
            <Speaker>PER0</Speaker>
          </token>
          <token id="11">
            <word>and</word>
            <lemma>and</lemma>
            <CharacterOffsetBegin>49</CharacterOffsetBegin>
            <CharacterOffsetEnd>52</CharacterOffsetEnd>
            <POS>CC</POS>
            <NER>O</NER>
            <Speaker>PER0</Speaker>
          </token>
          <token id="12">
            <word>Ross</word>
            <lemma>Ross</lemma>
            <CharacterOffsetBegin>53</CharacterOffsetBegin>
            <CharacterOffsetEnd>57</CharacterOffsetEnd>
            <POS>NNP</POS>
            <NER>PERSON</NER>
            <Speaker>PER0</Speaker>
          </token>
          <token id="13">
            <word>Syllabus</word>
            <lemma>Syllabus</lemma>
            <CharacterOffsetBegin>58</CharacterOffsetBegin>
            <CharacterOffsetEnd>66</CharacterOffsetEnd>
            <POS>NNP</POS>
            <NER>O</NER>
            <Speaker>PER0</Speaker>
          </token>
          <token id="14">
            <word>have</word>
            <lemma>have</lemma>
            <CharacterOffsetBegin>67</CharacterOffsetBegin>
            <CharacterOffsetEnd>71</CharacterOffsetEnd>
            <POS>VBP</POS>
            <NER>O</NER>
            <Speaker>PER0</Speaker>
          </token>
          <token id="15">
            <word>started</word>
            <lemma>start</lemma>
            <CharacterOffsetBegin>72</CharacterOffsetBegin>
            <CharacterOffsetEnd>79</CharacterOffsetEnd>
            <POS>VBN</POS>
            <NER>O</NER>
            <Speaker>PER0</Speaker>
          </token>
          <token id="16">
            <word>a</word>
            <lemma>a</lemma>
            <CharacterOffsetBegin>80</CharacterOffsetBegin>
            <CharacterOffsetEnd>81</CharacterOffsetEnd>
            <POS>DT</POS>
            <NER>O</NER>
            <Speaker>PER0</Speaker>
          </token>
          <token id="17">
            <word>family</word>
            <lemma>family</lemma>
            <CharacterOffsetBegin>82</CharacterOffsetBegin>
            <CharacterOffsetEnd>88</CharacterOffsetEnd>
            <POS>NN</POS>
            <NER>O</NER>
            <Speaker>PER0</Speaker>
          </token>
          <token id="18">
            <word>.</word>
            <lemma>.</lemma>
            <CharacterOffsetBegin>88</CharacterOffsetBegin>
            <CharacterOffsetEnd>89</CharacterOffsetEnd>
            <POS>.</POS>
            <NER>O</NER>
            <Speaker>PER0</Speaker>
          </token>
        </tokens>
        <parse>(ROOT (S (SBAR (NP (DT A) (JJ few) (NNS years)) (IN after) (S (NP (PRP they)) (ADVP (RB first)) (VP (VBD met)))) (, ,) (NP (NNP Naomi) (NNP Armitage) (CC and) (NNP Ross) (NNP Syllabus)) (VP (VBP have) (VP (VBN started) (NP (DT a) (NN family)))) (. .))) </parse>
        <dependencies type="basic-dependencies">
          <dep type="root">
            <governor idx="0">ROOT</governor>
            <dependent idx="15">started</dependent>
          </dep>
          <dep type="det">
            <governor idx="3">years</governor>
            <dependent idx="1">A</dependent>
          </dep>
          <dep type="amod">
            <governor idx="3">years</governor>
            <dependent idx="2">few</dependent>
          </dep>
          <dep type="dep">
            <governor idx="7">met</governor>
            <dependent idx="3">years</dependent>
          </dep>
          <dep type="mark">
            <governor idx="7">met</governor>
            <dependent idx="4">after</dependent>
          </dep>
          <dep type="nsubj">
            <governor idx="7">met</governor>
            <dependent idx="5">they</dependent>
          </dep>
          <dep type="advmod">
            <governor idx="7">met</governor>
            <dependent idx="6">first</dependent>
          </dep>
          <dep type="advcl">
            <governor idx="15">started</governor>
            <dependent idx="7">met</dependent>
          </dep>
          <dep type="punct">
            <governor idx="15">started</governor>
            <dependent idx="8">,</dependent>
          </dep>
          <dep type="compound">
            <governor idx="10">Armitage</governor>
            <dependent idx="9">Naomi</dependent>
          </dep>
          <dep type="nsubj">
            <governor idx="15">started</governor>
            <dependent idx="10">Armitage</dependent>
          </dep>
          <dep type="cc">
            <governor idx="10">Armitage</governor>
            <dependent idx="11">and</dependent>
          </dep>
          <dep type="compound">
            <governor idx="13">Syllabus</governor>
            <dependent idx="12">Ross</dependent>
          </dep>
          <dep type="conj">
            <governor idx="10">Armitage</governor>
            <dependent idx="13">Syllabus</dependent>
          </dep>
          <dep type="aux">
            <governor idx="15">started</governor>
            <dependent idx="14">have</dependent>
          </dep>
          <dep type="det">
            <governor idx="17">family</governor>
            <dependent idx="16">a</dependent>
          </dep>
          <dep type="dobj">
            <governor idx="15">started</governor>
            <dependent idx="17">family</dependent>
          </dep>
          <dep type="punct">
            <governor idx="15">started</governor>
            <dependent idx="18">.</dependent>
          </dep>
        </dependencies>
        <dependencies type="collapsed-dependencies">
          <dep type="root">
            <governor idx="0">ROOT</governor>
            <dependent idx="15">started</dependent>
          </dep>
          <dep type="det">
            <governor idx="3">years</governor>
            <dependent idx="1">A</dependent>
          </dep>
          <dep type="amod">
            <governor idx="3">years</governor>
            <dependent idx="2">few</dependent>
          </dep>
          <dep type="dep">
            <governor idx="7">met</governor>
            <dependent idx="3">years</dependent>
          </dep>
          <dep type="mark">
            <governor idx="7">met</governor>
            <dependent idx="4">after</dependent>
          </dep>
          <dep type="nsubj">
            <governor idx="7">met</governor>
            <dependent idx="5">they</dependent>
          </dep>
          <dep type="advmod">
            <governor idx="7">met</governor>
            <dependent idx="6">first</dependent>
          </dep>
          <dep type="advcl">
            <governor idx="15">started</governor>
            <dependent idx="7">met</dependent>
          </dep>
          <dep type="punct">
            <governor idx="15">started</governor>
            <dependent idx="8">,</dependent>
          </dep>
          <dep type="compound">
            <governor idx="10">Armitage</governor>
            <dependent idx="9">Naomi</dependent>
          </dep>
          <dep type="nsubj">
            <governor idx="15">started</governor>
            <dependent idx="10">Armitage</dependent>
          </dep>
          <dep type="cc">
            <governor idx="10">Armitage</governor>
            <dependent idx="11">and</dependent>
          </dep>
          <dep type="compound">
            <governor idx="13">Syllabus</governor>
            <dependent idx="12">Ross</dependent>
          </dep>
          <dep type="conj:and">
            <governor idx="10">Armitage</governor>
            <dependent idx="13">Syllabus</dependent>
          </dep>
          <dep type="aux">
            <governor idx="15">started</governor>
            <dependent idx="14">have</dependent>
          </dep>
          <dep type="det">
            <governor idx="17">family</governor>
            <dependent idx="16">a</dependent>
          </dep>
          <dep type="dobj">
            <governor idx="15">started</governor>
            <dependent idx="17">family</dependent>
          </dep>
          <dep type="punct">
            <governor idx="15">started</governor>
            <dependent idx="18">.</dependent>
          </dep>
        </dependencies>
        <dependencies type="collapsed-ccprocessed-dependencies">
          <dep type="root">
            <governor idx="0">ROOT</governor>
            <dependent idx="15">started</dependent>
          </dep>
          <dep type="det">
            <governor idx="3">years</governor>
            <dependent idx="1">A</dependent>
          </dep>
          <dep type="amod">
            <governor idx="3">years</governor>
            <dependent idx="2">few</dependent>
          </dep>
          <dep type="dep">
            <governor idx="7">met</governor>
            <dependent idx="3">years</dependent>
          </dep>
          <dep type="mark">
            <governor idx="7">met</governor>
            <dependent idx="4">after</dependent>
          </dep>
          <dep type="nsubj">
            <governor idx="7">met</governor>
            <dependent idx="5">they</dependent>
          </dep>
          <dep type="advmod">
            <governor idx="7">met</governor>
            <dependent idx="6">first</dependent>
          </dep>
          <dep type="advcl">
            <governor idx="15">started</governor>
            <dependent idx="7">met</dependent>
          </dep>
          <dep type="punct">
            <governor idx="15">started</governor>
            <dependent idx="8">,</dependent>
          </dep>
          <dep type="compound">
            <governor idx="10">Armitage</governor>
            <dependent idx="9">Naomi</dependent>
          </dep>
          <dep type="nsubj">
            <governor idx="15">started</governor>
            <dependent idx="10">Armitage</dependent>
          </dep>
          <dep type="cc">
            <governor idx="10">Armitage</governor>
            <dependent idx="11">and</dependent>
          </dep>
          <dep type="compound">
            <governor idx="13">Syllabus</governor>
            <dependent idx="12">Ross</dependent>
          </dep>
          <dep type="conj:and">
            <governor idx="10">Armitage</governor>
            <dependent idx="13">Syllabus</dependent>
          </dep>
          <dep type="nsubj" extra="true">
            <governor idx="15">started</governor>
            <dependent idx="13">Syllabus</dependent>
          </dep>
          <dep type="aux">
            <governor idx="15">started</governor>
            <dependent idx="14">have</dependent>
          </dep>
          <dep type="det">
            <governor idx="17">family</governor>
            <dependent idx="16">a</dependent>
          </dep>
          <dep type="dobj">
            <governor idx="15">started</governor>
            <dependent idx="17">family</dependent>
          </dep>
          <dep type="punct">
            <governor idx="15">started</governor>
            <dependent idx="18">.</dependent>
          </dep>
        </dependencies>
        <dependencies type="enhanced-dependencies">
          <dep type="root">
            <governor idx="0">ROOT</governor>
            <dependent idx="15">started</dependent>
          </dep>
          <dep type="det">
            <governor idx="3">years</governor>
            <dependent idx="1">A</dependent>
          </dep>
          <dep type="amod">
            <governor idx="3">years</governor>
            <dependent idx="2">few</dependent>
          </dep>
          <dep type="dep">
            <governor idx="7">met</governor>
            <dependent idx="3">years</dependent>
          </dep>
          <dep type="mark">
            <governor idx="7">met</governor>
            <dependent idx="4">after</dependent>
          </dep>
          <dep type="nsubj">
            <governor idx="7">met</governor>
            <dependent idx="5">they</dependent>
          </dep>
          <dep type="advmod">
            <governor idx="7">met</governor>
            <dependent idx="6">first</dependent>
          </dep>
          <dep type="advcl:after">
            <governor idx="15">started</governor>
            <dependent idx="7">met</dependent>
          </dep>
          <dep type="punct">
            <governor idx="15">started</governor>
            <dependent idx="8">,</dependent>
          </dep>
          <dep type="compound">
            <governor idx="10">Armitage</governor>
            <dependent idx="9">Naomi</dependent>
          </dep>
          <dep type="nsubj">
            <governor idx="15">started</governor>
            <dependent idx="10">Armitage</dependent>
          </dep>
          <dep type="cc">
            <governor idx="10">Armitage</governor>
            <dependent idx="11">and</dependent>
          </dep>
          <dep type="compound">
            <governor idx="13">Syllabus</governor>
            <dependent idx="12">Ross</dependent>
          </dep>
          <dep type="conj:and">
            <governor idx="10">Armitage</governor>
            <dependent idx="13">Syllabus</dependent>
          </dep>
          <dep type="nsubj" extra="true">
            <governor idx="15">started</governor>
            <dependent idx="13">Syllabus</dependent>
          </dep>
          <dep type="aux">
            <governor idx="15">started</governor>
            <dependent idx="14">have</dependent>
          </dep>
          <dep type="det">
            <governor idx="17">family</governor>
            <dependent idx="16">a</dependent>
          </dep>
          <dep type="dobj">
            <governor idx="15">started</governor>
            <dependent idx="17">family</dependent>
          </dep>
          <dep type="punct">
            <governor idx="15">started</governor>
            <dependent idx="18">.</dependent>
          </dep>
        </dependencies>
        <dependencies type="enhanced-plus-plus-dependencies">
          <dep type="root">
            <governor idx="0">ROOT</governor>
            <dependent idx="15">started</dependent>
          </dep>
          <dep type="det">
            <governor idx="3">years</governor>
            <dependent idx="1">A</dependent>
          </dep>
          <dep type="amod">
            <governor idx="3">years</governor>
            <dependent idx="2">few</dependent>
          </dep>
          <dep type="dep">
            <governor idx="7">met</governor>
            <dependent idx="3">years</dependent>
          </dep>
          <dep type="mark">
            <governor idx="7">met</governor>
            <dependent idx="4">after</dependent>
          </dep>
          <dep type="nsubj">
            <governor idx="7">met</governor>
            <dependent idx="5">they</dependent>
          </dep>
          <dep type="advmod">
            <governor idx="7">met</governor>
            <dependent idx="6">first</dependent>
          </dep>
          <dep type="advcl:after">
            <governor idx="15">started</governor>
            <dependent idx="7">met</dependent>
          </dep>
          <dep type="punct">
            <governor idx="15">started</governor>
            <dependent idx="8">,</dependent>
          </dep>
          <dep type="compound">
            <governor idx="10">Armitage</governor>
            <dependent idx="9">Naomi</dependent>
          </dep>
          <dep type="nsubj">
            <governor idx="15">started</governor>
            <dependent idx="10">Armitage</dependent>
          </dep>
          <dep type="cc">
            <governor idx="10">Armitage</governor>
            <dependent idx="11">and</dependent>
          </dep>
          <dep type="compound">
            <governor idx="13">Syllabus</governor>
            <dependent idx="12">Ross</dependent>
          </dep>
          <dep type="conj:and">
            <governor idx="10">Armitage</governor>
            <dependent idx="13">Syllabus</dependent>
          </dep>
          <dep type="nsubj" extra="true">
            <governor idx="15">started</governor>
            <dependent idx="13">Syllabus</dependent>
          </dep>
          <dep type="aux">
            <governor idx="15">started</governor>
            <dependent idx="14">have</dependent>
          </dep>
          <dep type="det">
            <governor idx="17">family</governor>
            <dependent idx="16">a</dependent>
          </dep>
          <dep type="dobj">
            <governor idx="15">started</governor>
            <dependent idx="17">family</dependent>
          </dep>
          <dep type="punct">
            <governor idx="15">started</governor>
            <dependent idx="18">.</dependent>
          </dep>
        </dependencies>
      </sentence>
      <sentence id="2">
        <tokens>
          <token id="1">
            <word>Despite</word>
            <lemma>despite</lemma>
            <CharacterOffsetBegin>90</CharacterOffsetBegin>
            <CharacterOffsetEnd>97</CharacterOffsetEnd>
            <POS>IN</POS>
            <NER>O</NER>
            <Speaker>PER0</Speaker>
          </token>
          <token id="2">
            <word>their</word>
            <lemma>they</lemma>
            <CharacterOffsetBegin>98</CharacterOffsetBegin>
            <CharacterOffsetEnd>103</CharacterOffsetEnd>
            <POS>PRP$</POS>
            <NER>O</NER>
            <Speaker>PER0</Speaker>
          </token>
          <token id="3">
            <word>normal</word>
            <lemma>normal</lemma>
            <CharacterOffsetBegin>104</CharacterOffsetBegin>
            <CharacterOffsetEnd>110</CharacterOffsetEnd>
            <POS>JJ</POS>
            <NER>O</NER>
            <Speaker>PER0</Speaker>
          </token>
          <token id="4">
            <word>lives</word>
            <lemma>life</lemma>
            <CharacterOffsetBegin>111</CharacterOffsetBegin>
            <CharacterOffsetEnd>116</CharacterOffsetEnd>
            <POS>NNS</POS>
            <NER>O</NER>
            <Speaker>PER0</Speaker>
          </token>
          <token id="5">
            <word>,</word>
            <lemma>,</lemma>
            <CharacterOffsetBegin>116</CharacterOffsetBegin>
            <CharacterOffsetEnd>117</CharacterOffsetEnd>
            <POS>,</POS>
            <NER>O</NER>
            <Speaker>PER0</Speaker>
          </token>
          <token id="6">
            <word>they</word>
            <lemma>they</lemma>
            <CharacterOffsetBegin>118</CharacterOffsetBegin>
            <CharacterOffsetEnd>122</CharacterOffsetEnd>
            <POS>PRP</POS>
            <NER>O</NER>
            <Speaker>PER0</Speaker>
          </token>
          <token id="7">
            <word>must</word>
            <lemma>must</lemma>
            <CharacterOffsetBegin>123</CharacterOffsetBegin>
            <CharacterOffsetEnd>127</CharacterOffsetEnd>
            <POS>MD</POS>
            <NER>O</NER>
            <Speaker>PER0</Speaker>
          </token>
          <token id="8">
            <word>keep</word>
            <lemma>keep</lemma>
            <CharacterOffsetBegin>128</CharacterOffsetBegin>
            <CharacterOffsetEnd>132</CharacterOffsetEnd>
            <POS>VB</POS>
            <NER>O</NER>
            <Speaker>PER0</Speaker>
          </token>
          <token id="9">
            <word>their</word>
            <lemma>they</lemma>
            <CharacterOffsetBegin>133</CharacterOffsetBegin>
            <CharacterOffsetEnd>138</CharacterOffsetEnd>
            <POS>PRP$</POS>
            <NER>O</NER>
            <Speaker>PER0</Speaker>
          </token>
          <token id="10">
            <word>identities</word>
            <lemma>identity</lemma>
            <CharacterOffsetBegin>139</CharacterOffsetBegin>
            <CharacterOffsetEnd>149</CharacterOffsetEnd>
            <POS>NNS</POS>
            <NER>O</NER>
            <Speaker>PER0</Speaker>
          </token>
          <token id="11">
            <word>a</word>
            <lemma>a</lemma>
            <CharacterOffsetBegin>150</CharacterOffsetBegin>
            <CharacterOffsetEnd>151</CharacterOffsetEnd>
            <POS>DT</POS>
            <NER>O</NER>
            <Speaker>PER0</Speaker>
          </token>
          <token id="12">
            <word>secret</word>
            <lemma>secret</lemma>
            <CharacterOffsetBegin>152</CharacterOffsetBegin>
            <CharacterOffsetEnd>158</CharacterOffsetEnd>
            <POS>NN</POS>
            <NER>O</NER>
            <Speaker>PER0</Speaker>
          </token>
          <token id="13">
            <word>because</word>
            <lemma>because</lemma>
            <CharacterOffsetBegin>159</CharacterOffsetBegin>
            <CharacterOffsetEnd>166</CharacterOffsetEnd>
            <POS>IN</POS>
            <NER>O</NER>
            <Speaker>PER0</Speaker>
          </token>
          <token id="14">
            <word>many</word>
            <lemma>many</lemma>
            <CharacterOffsetBegin>167</CharacterOffsetBegin>
            <CharacterOffsetEnd>171</CharacterOffsetEnd>
            <POS>JJ</POS>
            <NER>O</NER>
            <Speaker>PER0</Speaker>
          </token>
          <token id="15">
            <word>people</word>
            <lemma>people</lemma>
            <CharacterOffsetBegin>172</CharacterOffsetBegin>
            <CharacterOffsetEnd>178</CharacterOffsetEnd>
            <POS>NNS</POS>
            <NER>O</NER>
            <Speaker>PER0</Speaker>
          </token>
          <token id="16">
            <word>believe</word>
            <lemma>believe</lemma>
            <CharacterOffsetBegin>179</CharacterOffsetBegin>
            <CharacterOffsetEnd>186</CharacterOffsetEnd>
            <POS>VBP</POS>
            <NER>O</NER>
            <Speaker>PER0</Speaker>
          </token>
          <token id="17">
            <word>that</word>
            <lemma>that</lemma>
            <CharacterOffsetBegin>187</CharacterOffsetBegin>
            <CharacterOffsetEnd>191</CharacterOffsetEnd>
            <POS>IN</POS>
            <NER>O</NER>
            <Speaker>PER0</Speaker>
          </token>
          <token id="18">
            <word>Robots</word>
            <lemma>robot</lemma>
            <CharacterOffsetBegin>192</CharacterOffsetBegin>
            <CharacterOffsetEnd>198</CharacterOffsetEnd>
            <POS>NNS</POS>
            <NER>O</NER>
            <Speaker>PER0</Speaker>
          </token>
          <token id="19">
            <word>do</word>
            <lemma>do</lemma>
            <CharacterOffsetBegin>199</CharacterOffsetBegin>
            <CharacterOffsetEnd>201</CharacterOffsetEnd>
            <POS>VBP</POS>
            <NER>O</NER>
            <Speaker>PER0</Speaker>
          </token>
          <token id="20">
            <word>not</word>
            <lemma>not</lemma>
            <CharacterOffsetBegin>202</CharacterOffsetBegin>
            <CharacterOffsetEnd>205</CharacterOffsetEnd>
            <POS>RB</POS>
            <NER>O</NER>
            <Speaker>PER0</Speaker>
          </token>
          <token id="21">
            <word>deserve</word>
            <lemma>deserve</lemma>
            <CharacterOffsetBegin>206</CharacterOffsetBegin>
            <CharacterOffsetEnd>213</CharacterOffsetEnd>
            <POS>VB</POS>
            <NER>O</NER>
            <Speaker>PER0</Speaker>
          </token>
          <token id="22">
            <word>equal</word>
            <lemma>equal</lemma>
            <CharacterOffsetBegin>214</CharacterOffsetBegin>
            <CharacterOffsetEnd>219</CharacterOffsetEnd>
            <POS>JJ</POS>
            <NER>O</NER>
            <Speaker>PER0</Speaker>
          </token>
          <token id="23">
            <word>status</word>
            <lemma>status</lemma>
            <CharacterOffsetBegin>220</CharacterOffsetBegin>
            <CharacterOffsetEnd>226</CharacterOffsetEnd>
            <POS>NN</POS>
            <NER>O</NER>
            <Speaker>PER0</Speaker>
          </token>
          <token id="24">
            <word>with</word>
            <lemma>with</lemma>
            <CharacterOffsetBegin>227</CharacterOffsetBegin>
            <CharacterOffsetEnd>231</CharacterOffsetEnd>
            <POS>IN</POS>
            <NER>O</NER>
            <Speaker>PER0</Speaker>
          </token>
          <token id="25">
            <word>humans</word>
            <lemma>human</lemma>
            <CharacterOffsetBegin>232</CharacterOffsetBegin>
            <CharacterOffsetEnd>238</CharacterOffsetEnd>
            <POS>NNS</POS>
            <NER>O</NER>
            <Speaker>PER0</Speaker>
          </token>
          <token id="26">
            <word>.</word>
            <lemma>.</lemma>
            <CharacterOffsetBegin>238</CharacterOffsetBegin>
            <CharacterOffsetEnd>239</CharacterOffsetEnd>
            <POS>.</POS>
            <NER>O</NER>
            <Speaker>PER0</Speaker>
          </token>
        </tokens>
        <parse>(ROOT (S (PP (IN Despite) (NP (PRP$ their) (JJ normal) (NNS lives))) (, ,) (NP (PRP they)) (VP (MD must) (VP (VB keep) (NP (PRP$ their) (NNS identities)) (NP (NP (DT a) (NN secret)) (SBAR (IN because) (S (NP (JJ many) (NNS people)) (VP (VBP believe) (SBAR (IN that) (S (NP (NNS Robots)) (VP (VBP do) (RB not) (VP (VB deserve) (NP (JJ equal) (NN status)) (PP (IN with) (NP (NNS humans))))))))))))) (. .))) </parse>
        <dependencies type="basic-dependencies">
          <dep type="root">
            <governor idx="0">ROOT</governor>
            <dependent idx="8">keep</dependent>
          </dep>
          <dep type="case">
            <governor idx="4">lives</governor>
            <dependent idx="1">Despite</dependent>
          </dep>
          <dep type="nmod:poss">
            <governor idx="4">lives</governor>
            <dependent idx="2">their</dependent>
          </dep>
          <dep type="amod">
            <governor idx="4">lives</governor>
            <dependent idx="3">normal</dependent>
          </dep>
          <dep type="nmod">
            <governor idx="8">keep</governor>
            <dependent idx="4">lives</dependent>
          </dep>
          <dep type="punct">
            <governor idx="8">keep</governor>
            <dependent idx="5">,</dependent>
          </dep>
          <dep type="nsubj">
            <governor idx="8">keep</governor>
            <dependent idx="6">they</dependent>
          </dep>
          <dep type="aux">
            <governor idx="8">keep</governor>
            <dependent idx="7">must</dependent>
          </dep>
          <dep type="nmod:poss">
            <governor idx="10">identities</governor>
            <dependent idx="9">their</dependent>
          </dep>
          <dep type="dep">
            <governor idx="8">keep</governor>
            <dependent idx="10">identities</dependent>
          </dep>
          <dep type="det">
            <governor idx="12">secret</governor>
            <dependent idx="11">a</dependent>
          </dep>
          <dep type="dobj">
            <governor idx="8">keep</governor>
            <dependent idx="12">secret</dependent>
          </dep>
          <dep type="mark">
            <governor idx="16">believe</governor>
            <dependent idx="13">because</dependent>
          </dep>
          <dep type="amod">
            <governor idx="15">people</governor>
            <dependent idx="14">many</dependent>
          </dep>
          <dep type="nsubj">
            <governor idx="16">believe</governor>
            <dependent idx="15">people</dependent>
          </dep>
          <dep type="dep">
            <governor idx="12">secret</governor>
            <dependent idx="16">believe</dependent>
          </dep>
          <dep type="mark">
            <governor idx="21">deserve</governor>
            <dependent idx="17">that</dependent>
          </dep>
          <dep type="nsubj">
            <governor idx="21">deserve</governor>
            <dependent idx="18">Robots</dependent>
          </dep>
          <dep type="aux">
            <governor idx="21">deserve</governor>
            <dependent idx="19">do</dependent>
          </dep>
          <dep type="neg">
            <governor idx="21">deserve</governor>
            <dependent idx="20">not</dependent>
          </dep>
          <dep type="ccomp">
            <governor idx="16">believe</governor>
            <dependent idx="21">deserve</dependent>
          </dep>
          <dep type="amod">
            <governor idx="23">status</governor>
            <dependent idx="22">equal</dependent>
          </dep>
          <dep type="dobj">
            <governor idx="21">deserve</governor>
            <dependent idx="23">status</dependent>
          </dep>
          <dep type="case">
            <governor idx="25">humans</governor>
            <dependent idx="24">with</dependent>
          </dep>
          <dep type="nmod">
            <governor idx="21">deserve</governor>
            <dependent idx="25">humans</dependent>
          </dep>
          <dep type="punct">
            <governor idx="8">keep</governor>
            <dependent idx="26">.</dependent>
          </dep>
        </dependencies>
        <dependencies type="collapsed-dependencies">
          <dep type="root">
            <governor idx="0">ROOT</governor>
            <dependent idx="8">keep</dependent>
          </dep>
          <dep type="case">
            <governor idx="4">lives</governor>
            <dependent idx="1">Despite</dependent>
          </dep>
          <dep type="nmod:poss">
            <governor idx="4">lives</governor>
            <dependent idx="2">their</dependent>
          </dep>
          <dep type="amod">
            <governor idx="4">lives</governor>
            <dependent idx="3">normal</dependent>
          </dep>
          <dep type="nmod:despite">
            <governor idx="8">keep</governor>
            <dependent idx="4">lives</dependent>
          </dep>
          <dep type="punct">
            <governor idx="8">keep</governor>
            <dependent idx="5">,</dependent>
          </dep>
          <dep type="nsubj">
            <governor idx="8">keep</governor>
            <dependent idx="6">they</dependent>
          </dep>
          <dep type="aux">
            <governor idx="8">keep</governor>
            <dependent idx="7">must</dependent>
          </dep>
          <dep type="nmod:poss">
            <governor idx="10">identities</governor>
            <dependent idx="9">their</dependent>
          </dep>
          <dep type="dep">
            <governor idx="8">keep</governor>
            <dependent idx="10">identities</dependent>
          </dep>
          <dep type="det">
            <governor idx="12">secret</governor>
            <dependent idx="11">a</dependent>
          </dep>
          <dep type="dobj">
            <governor idx="8">keep</governor>
            <dependent idx="12">secret</dependent>
          </dep>
          <dep type="mark">
            <governor idx="16">believe</governor>
            <dependent idx="13">because</dependent>
          </dep>
          <dep type="amod">
            <governor idx="15">people</governor>
            <dependent idx="14">many</dependent>
          </dep>
          <dep type="nsubj">
            <governor idx="16">believe</governor>
            <dependent idx="15">people</dependent>
          </dep>
          <dep type="dep">
            <governor idx="12">secret</governor>
            <dependent idx="16">believe</dependent>
          </dep>
          <dep type="mark">
            <governor idx="21">deserve</governor>
            <dependent idx="17">that</dependent>
          </dep>
          <dep type="nsubj">
            <governor idx="21">deserve</governor>
            <dependent idx="18">Robots</dependent>
          </dep>
          <dep type="aux">
            <governor idx="21">deserve</governor>
            <dependent idx="19">do</dependent>
          </dep>
          <dep type="neg">
            <governor idx="21">deserve</governor>
            <dependent idx="20">not</dependent>
          </dep>
          <dep type="ccomp">
            <governor idx="16">believe</governor>
            <dependent idx="21">deserve</dependent>
          </dep>
          <dep type="amod">
            <governor idx="23">status</governor>
            <dependent idx="22">equal</dependent>
          </dep>
          <dep type="dobj">
            <governor idx="21">deserve</governor>
            <dependent idx="23">status</dependent>
          </dep>
          <dep type="case">
            <governor idx="25">humans</governor>
            <dependent idx="24">with</dependent>
          </dep>
          <dep type="nmod:with">
            <governor idx="21">deserve</governor>
            <dependent idx="25">humans</dependent>
          </dep>
          <dep type="punct">
            <governor idx="8">keep</governor>
            <dependent idx="26">.</dependent>
          </dep>
        </dependencies>
        <dependencies type="collapsed-ccprocessed-dependencies">
          <dep type="root">
            <governor idx="0">ROOT</governor>
            <dependent idx="8">keep</dependent>
          </dep>
          <dep type="case">
            <governor idx="4">lives</governor>
            <dependent idx="1">Despite</dependent>
          </dep>
          <dep type="nmod:poss">
            <governor idx="4">lives</governor>
            <dependent idx="2">their</dependent>
          </dep>
          <dep type="amod">
            <governor idx="4">lives</governor>
            <dependent idx="3">normal</dependent>
          </dep>
          <dep type="nmod:despite">
            <governor idx="8">keep</governor>
            <dependent idx="4">lives</dependent>
          </dep>
          <dep type="punct">
            <governor idx="8">keep</governor>
            <dependent idx="5">,</dependent>
          </dep>
          <dep type="nsubj">
            <governor idx="8">keep</governor>
            <dependent idx="6">they</dependent>
          </dep>
          <dep type="aux">
            <governor idx="8">keep</governor>
            <dependent idx="7">must</dependent>
          </dep>
          <dep type="nmod:poss">
            <governor idx="10">identities</governor>
            <dependent idx="9">their</dependent>
          </dep>
          <dep type="dep">
            <governor idx="8">keep</governor>
            <dependent idx="10">identities</dependent>
          </dep>
          <dep type="det">
            <governor idx="12">secret</governor>
            <dependent idx="11">a</dependent>
          </dep>
          <dep type="dobj">
            <governor idx="8">keep</governor>
            <dependent idx="12">secret</dependent>
          </dep>
          <dep type="mark">
            <governor idx="16">believe</governor>
            <dependent idx="13">because</dependent>
          </dep>
          <dep type="amod">
            <governor idx="15">people</governor>
            <dependent idx="14">many</dependent>
          </dep>
          <dep type="nsubj">
            <governor idx="16">believe</governor>
            <dependent idx="15">people</dependent>
          </dep>
          <dep type="dep">
            <governor idx="12">secret</governor>
            <dependent idx="16">believe</dependent>
          </dep>
          <dep type="mark">
            <governor idx="21">deserve</governor>
            <dependent idx="17">that</dependent>
          </dep>
          <dep type="nsubj">
            <governor idx="21">deserve</governor>
            <dependent idx="18">Robots</dependent>
          </dep>
          <dep type="aux">
            <governor idx="21">deserve</governor>
            <dependent idx="19">do</dependent>
          </dep>
          <dep type="neg">
            <governor idx="21">deserve</governor>
            <dependent idx="20">not</dependent>
          </dep>
          <dep type="ccomp">
            <governor idx="16">believe</governor>
            <dependent idx="21">deserve</dependent>
          </dep>
          <dep type="amod">
            <governor idx="23">status</governor>
            <dependent idx="22">equal</dependent>
          </dep>
          <dep type="dobj">
            <governor idx="21">deserve</governor>
            <dependent idx="23">status</dependent>
          </dep>
          <dep type="case">
            <governor idx="25">humans</governor>
            <dependent idx="24">with</dependent>
          </dep>
          <dep type="nmod:with">
            <governor idx="21">deserve</governor>
            <dependent idx="25">humans</dependent>
          </dep>
          <dep type="punct">
            <governor idx="8">keep</governor>
            <dependent idx="26">.</dependent>
          </dep>
        </dependencies>
        <dependencies type="enhanced-dependencies">
          <dep type="root">
            <governor idx="0">ROOT</governor>
            <dependent idx="8">keep</dependent>
          </dep>
          <dep type="case">
            <governor idx="4">lives</governor>
            <dependent idx="1">Despite</dependent>
          </dep>
          <dep type="nmod:poss">
            <governor idx="4">lives</governor>
            <dependent idx="2">their</dependent>
          </dep>
          <dep type="amod">
            <governor idx="4">lives</governor>
            <dependent idx="3">normal</dependent>
          </dep>
          <dep type="nmod:despite">
            <governor idx="8">keep</governor>
            <dependent idx="4">lives</dependent>
          </dep>
          <dep type="punct">
            <governor idx="8">keep</governor>
            <dependent idx="5">,</dependent>
          </dep>
          <dep type="nsubj">
            <governor idx="8">keep</governor>
            <dependent idx="6">they</dependent>
          </dep>
          <dep type="aux">
            <governor idx="8">keep</governor>
            <dependent idx="7">must</dependent>
          </dep>
          <dep type="nmod:poss">
            <governor idx="10">identities</governor>
            <dependent idx="9">their</dependent>
          </dep>
          <dep type="dep">
            <governor idx="8">keep</governor>
            <dependent idx="10">identities</dependent>
          </dep>
          <dep type="det">
            <governor idx="12">secret</governor>
            <dependent idx="11">a</dependent>
          </dep>
          <dep type="dobj">
            <governor idx="8">keep</governor>
            <dependent idx="12">secret</dependent>
          </dep>
          <dep type="mark">
            <governor idx="16">believe</governor>
            <dependent idx="13">because</dependent>
          </dep>
          <dep type="amod">
            <governor idx="15">people</governor>
            <dependent idx="14">many</dependent>
          </dep>
          <dep type="nsubj">
            <governor idx="16">believe</governor>
            <dependent idx="15">people</dependent>
          </dep>
          <dep type="dep">
            <governor idx="12">secret</governor>
            <dependent idx="16">believe</dependent>
          </dep>
          <dep type="mark">
            <governor idx="21">deserve</governor>
            <dependent idx="17">that</dependent>
          </dep>
          <dep type="nsubj">
            <governor idx="21">deserve</governor>
            <dependent idx="18">Robots</dependent>
          </dep>
          <dep type="aux">
            <governor idx="21">deserve</governor>
            <dependent idx="19">do</dependent>
          </dep>
          <dep type="neg">
            <governor idx="21">deserve</governor>
            <dependent idx="20">not</dependent>
          </dep>
          <dep type="ccomp">
            <governor idx="16">believe</governor>
            <dependent idx="21">deserve</dependent>
          </dep>
          <dep type="amod">
            <governor idx="23">status</governor>
            <dependent idx="22">equal</dependent>
          </dep>
          <dep type="dobj">
            <governor idx="21">deserve</governor>
            <dependent idx="23">status</dependent>
          </dep>
          <dep type="case">
            <governor idx="25">humans</governor>
            <dependent idx="24">with</dependent>
          </dep>
          <dep type="nmod:with">
            <governor idx="21">deserve</governor>
            <dependent idx="25">humans</dependent>
          </dep>
          <dep type="punct">
            <governor idx="8">keep</governor>
            <dependent idx="26">.</dependent>
          </dep>
        </dependencies>
        <dependencies type="enhanced-plus-plus-dependencies">
          <dep type="root">
            <governor idx="0">ROOT</governor>
            <dependent idx="8">keep</dependent>
          </dep>
          <dep type="case">
            <governor idx="4">lives</governor>
            <dependent idx="1">Despite</dependent>
          </dep>
          <dep type="nmod:poss">
            <governor idx="4">lives</governor>
            <dependent idx="2">their</dependent>
          </dep>
          <dep type="amod">
            <governor idx="4">lives</governor>
            <dependent idx="3">normal</dependent>
          </dep>
          <dep type="nmod:despite">
            <governor idx="8">keep</governor>
            <dependent idx="4">lives</dependent>
          </dep>
          <dep type="punct">
            <governor idx="8">keep</governor>
            <dependent idx="5">,</dependent>
          </dep>
          <dep type="nsubj">
            <governor idx="8">keep</governor>
            <dependent idx="6">they</dependent>
          </dep>
          <dep type="aux">
            <governor idx="8">keep</governor>
            <dependent idx="7">must</dependent>
          </dep>
          <dep type="nmod:poss">
            <governor idx="10">identities</governor>
            <dependent idx="9">their</dependent>
          </dep>
          <dep type="dep">
            <governor idx="8">keep</governor>
            <dependent idx="10">identities</dependent>
          </dep>
          <dep type="det">
            <governor idx="12">secret</governor>
            <dependent idx="11">a</dependent>
          </dep>
          <dep type="dobj">
            <governor idx="8">keep</governor>
            <dependent idx="12">secret</dependent>
          </dep>
          <dep type="mark">
            <governor idx="16">believe</governor>
            <dependent idx="13">because</dependent>
          </dep>
          <dep type="amod">
            <governor idx="15">people</governor>
            <dependent idx="14">many</dependent>
          </dep>
          <dep type="nsubj">
            <governor idx="16">believe</governor>
            <dependent idx="15">people</dependent>
          </dep>
          <dep type="dep">
            <governor idx="12">secret</governor>
            <dependent idx="16">believe</dependent>
          </dep>
          <dep type="mark">
            <governor idx="21">deserve</governor>
            <dependent idx="17">that</dependent>
          </dep>
          <dep type="nsubj">
            <governor idx="21">deserve</governor>
            <dependent idx="18">Robots</dependent>
          </dep>
          <dep type="aux">
            <governor idx="21">deserve</governor>
            <dependent idx="19">do</dependent>
          </dep>
          <dep type="neg">
            <governor idx="21">deserve</governor>
            <dependent idx="20">not</dependent>
          </dep>
          <dep type="ccomp">
            <governor idx="16">believe</governor>
            <dependent idx="21">deserve</dependent>
          </dep>
          <dep type="amod">
            <governor idx="23">status</governor>
            <dependent idx="22">equal</dependent>
          </dep>
          <dep type="dobj">
            <governor idx="21">deserve</governor>
            <dependent idx="23">status</dependent>
          </dep>
          <dep type="case">
            <governor idx="25">humans</governor>
            <dependent idx="24">with</dependent>
          </dep>
          <dep type="nmod:with">
            <governor idx="21">deserve</governor>
            <dependent idx="25">humans</dependent>
          </dep>
          <dep type="punct">
            <governor idx="8">keep</governor>
            <dependent idx="26">.</dependent>
          </dep>
        </dependencies>
      </sentence>
      <sentence id="3">
        <tokens>
          <token id="1">
            <word>Ross</word>
            <lemma>Ross</lemma>
            <CharacterOffsetBegin>240</CharacterOffsetBegin>
            <CharacterOffsetEnd>244</CharacterOffsetEnd>
            <POS>NNP</POS>
            <NER>PERSON</NER>
            <Speaker>PER0</Speaker>
          </token>
          <token id="2">
            <word>has</word>
            <lemma>have</lemma>
            <CharacterOffsetBegin>245</CharacterOffsetBegin>
            <CharacterOffsetEnd>248</CharacterOffsetEnd>
            <POS>VBZ</POS>
            <NER>O</NER>
            <Speaker>PER0</Speaker>
          </token>
          <token id="3">
            <word>an</word>
            <lemma>a</lemma>
            <CharacterOffsetBegin>249</CharacterOffsetBegin>
            <CharacterOffsetEnd>251</CharacterOffsetEnd>
            <POS>DT</POS>
            <NER>O</NER>
            <Speaker>PER0</Speaker>
          </token>
          <token id="4">
            <word>opportunity</word>
            <lemma>opportunity</lemma>
            <CharacterOffsetBegin>252</CharacterOffsetBegin>
            <CharacterOffsetEnd>263</CharacterOffsetEnd>
            <POS>NN</POS>
            <NER>O</NER>
            <Speaker>PER0</Speaker>
          </token>
          <token id="5">
            <word>to</word>
            <lemma>to</lemma>
            <CharacterOffsetBegin>264</CharacterOffsetBegin>
            <CharacterOffsetEnd>266</CharacterOffsetEnd>
            <POS>TO</POS>
            <NER>O</NER>
            <Speaker>PER0</Speaker>
          </token>
          <token id="6">
            <word>abolish</word>
            <lemma>abolish</lemma>
            <CharacterOffsetBegin>267</CharacterOffsetBegin>
            <CharacterOffsetEnd>274</CharacterOffsetEnd>
            <POS>VB</POS>
            <NER>O</NER>
            <Speaker>PER0</Speaker>
          </token>
          <token id="7">
            <word>these</word>
            <lemma>these</lemma>
            <CharacterOffsetBegin>275</CharacterOffsetBegin>
            <CharacterOffsetEnd>280</CharacterOffsetEnd>
            <POS>DT</POS>
            <NER>O</NER>
            <Speaker>PER0</Speaker>
          </token>
          <token id="8">
            <word>ideas</word>
            <lemma>idea</lemma>
            <CharacterOffsetBegin>281</CharacterOffsetBegin>
            <CharacterOffsetEnd>286</CharacterOffsetEnd>
            <POS>NNS</POS>
            <NER>O</NER>
            <Speaker>PER0</Speaker>
          </token>
          <token id="9">
            <word>on</word>
            <lemma>on</lemma>
            <CharacterOffsetBegin>287</CharacterOffsetBegin>
            <CharacterOffsetEnd>289</CharacterOffsetEnd>
            <POS>IN</POS>
            <NER>O</NER>
            <Speaker>PER0</Speaker>
          </token>
          <token id="10">
            <word>Earth</word>
            <lemma>Earth</lemma>
            <CharacterOffsetBegin>290</CharacterOffsetBegin>
            <CharacterOffsetEnd>295</CharacterOffsetEnd>
            <POS>NNP</POS>
            <NER>O</NER>
            <Speaker>PER0</Speaker>
          </token>
          <token id="11">
            <word>through</word>
            <lemma>through</lemma>
            <CharacterOffsetBegin>296</CharacterOffsetBegin>
            <CharacterOffsetEnd>303</CharacterOffsetEnd>
            <POS>IN</POS>
            <NER>O</NER>
            <Speaker>PER0</Speaker>
          </token>
          <token id="12">
            <word>a</word>
            <lemma>a</lemma>
            <CharacterOffsetBegin>304</CharacterOffsetBegin>
            <CharacterOffsetEnd>305</CharacterOffsetEnd>
            <POS>DT</POS>
            <NER>O</NER>
            <Speaker>PER0</Speaker>
          </token>
          <token id="13">
            <word>vote</word>
            <lemma>vote</lemma>
            <CharacterOffsetBegin>306</CharacterOffsetBegin>
            <CharacterOffsetEnd>310</CharacterOffsetEnd>
            <POS>NN</POS>
            <NER>O</NER>
            <Speaker>PER0</Speaker>
          </token>
          <token id="14">
            <word>,</word>
            <lemma>,</lemma>
            <CharacterOffsetBegin>310</CharacterOffsetBegin>
            <CharacterOffsetEnd>311</CharacterOffsetEnd>
            <POS>,</POS>
            <NER>O</NER>
            <Speaker>PER0</Speaker>
          </token>
          <token id="15">
            <word>but</word>
            <lemma>but</lemma>
            <CharacterOffsetBegin>312</CharacterOffsetBegin>
            <CharacterOffsetEnd>315</CharacterOffsetEnd>
            <POS>CC</POS>
            <NER>O</NER>
            <Speaker>PER0</Speaker>
          </token>
          <token id="16">
            <word>organizations</word>
            <lemma>organization</lemma>
            <CharacterOffsetBegin>316</CharacterOffsetBegin>
            <CharacterOffsetEnd>329</CharacterOffsetEnd>
            <POS>NNS</POS>
            <NER>O</NER>
            <Speaker>PER0</Speaker>
          </token>
          <token id="17">
            <word>in</word>
            <lemma>in</lemma>
            <CharacterOffsetBegin>330</CharacterOffsetBegin>
            <CharacterOffsetEnd>332</CharacterOffsetEnd>
            <POS>IN</POS>
            <NER>O</NER>
            <Speaker>PER0</Speaker>
          </token>
          <token id="18">
            <word>the</word>
            <lemma>the</lemma>
            <CharacterOffsetBegin>333</CharacterOffsetBegin>
            <CharacterOffsetEnd>336</CharacterOffsetEnd>
            <POS>DT</POS>
            <NER>O</NER>
            <Speaker>PER0</Speaker>
          </token>
          <token id="19">
            <word>shadows</word>
            <lemma>shadow</lemma>
            <CharacterOffsetBegin>337</CharacterOffsetBegin>
            <CharacterOffsetEnd>344</CharacterOffsetEnd>
            <POS>NNS</POS>
            <NER>O</NER>
            <Speaker>PER0</Speaker>
          </token>
          <token id="20">
            <word>are</word>
            <lemma>be</lemma>
            <CharacterOffsetBegin>345</CharacterOffsetBegin>
            <CharacterOffsetEnd>348</CharacterOffsetEnd>
            <POS>VBP</POS>
            <NER>O</NER>
            <Speaker>PER0</Speaker>
          </token>
          <token id="21">
            <word>working</word>
            <lemma>work</lemma>
            <CharacterOffsetBegin>349</CharacterOffsetBegin>
            <CharacterOffsetEnd>356</CharacterOffsetEnd>
            <POS>VBG</POS>
            <NER>O</NER>
            <Speaker>PER0</Speaker>
          </token>
          <token id="22">
            <word>so</word>
            <lemma>so</lemma>
            <CharacterOffsetBegin>357</CharacterOffsetBegin>
            <CharacterOffsetEnd>359</CharacterOffsetEnd>
            <POS>RB</POS>
            <NER>O</NER>
            <Speaker>PER0</Speaker>
          </token>
          <token id="23">
            <word>that</word>
            <lemma>that</lemma>
            <CharacterOffsetBegin>360</CharacterOffsetBegin>
            <CharacterOffsetEnd>364</CharacterOffsetEnd>
            <POS>IN</POS>
            <NER>O</NER>
            <Speaker>PER0</Speaker>
          </token>
          <token id="24">
            <word>it</word>
            <lemma>it</lemma>
            <CharacterOffsetBegin>365</CharacterOffsetBegin>
            <CharacterOffsetEnd>367</CharacterOffsetEnd>
            <POS>PRP</POS>
            <NER>O</NER>
            <Speaker>PER0</Speaker>
          </token>
          <token id="25">
            <word>does</word>
            <lemma>do</lemma>
            <CharacterOffsetBegin>368</CharacterOffsetBegin>
            <CharacterOffsetEnd>372</CharacterOffsetEnd>
            <POS>VBZ</POS>
            <NER>O</NER>
            <Speaker>PER0</Speaker>
          </token>
          <token id="26">
            <word>n't</word>
            <lemma>not</lemma>
            <CharacterOffsetBegin>372</CharacterOffsetBegin>
            <CharacterOffsetEnd>375</CharacterOffsetEnd>
            <POS>RB</POS>
            <NER>O</NER>
            <Speaker>PER0</Speaker>
          </token>
          <token id="27">
            <word>happen</word>
            <lemma>happen</lemma>
            <CharacterOffsetBegin>376</CharacterOffsetBegin>
            <CharacterOffsetEnd>382</CharacterOffsetEnd>
            <POS>VB</POS>
            <NER>O</NER>
            <Speaker>PER0</Speaker>
          </token>
          <token id="28">
            <word>.</word>
            <lemma>.</lemma>
            <CharacterOffsetBegin>382</CharacterOffsetBegin>
            <CharacterOffsetEnd>383</CharacterOffsetEnd>
            <POS>.</POS>
            <NER>O</NER>
            <Speaker>PER0</Speaker>
          </token>
        </tokens>
        <parse>(ROOT (S (S (NP (NNP Ross)) (VP (VBZ has) (NP (DT an) (NN opportunity) (S (VP (TO to) (VP (VB abolish) (NP (NP (DT these) (NNS ideas)) (PP (IN on) (NP (NNP Earth)))) (PP (IN through) (NP (DT a) (NN vote))))))))) (, ,) (CC but) (S (NP (NP (NNS organizations)) (PP (IN in) (NP (DT the) (NNS shadows)))) (VP (VBP are) (VP (VBG working) (SBAR (RB so) (IN that) (S (NP (PRP it)) (VP (VBZ does) (RB n't) (VP (VB happen)))))))) (. .))) </parse>
        <dependencies type="basic-dependencies">
          <dep type="root">
            <governor idx="0">ROOT</governor>
            <dependent idx="2">has</dependent>
          </dep>
          <dep type="nsubj">
            <governor idx="2">has</governor>
            <dependent idx="1">Ross</dependent>
          </dep>
          <dep type="det">
            <governor idx="4">opportunity</governor>
            <dependent idx="3">an</dependent>
          </dep>
          <dep type="dobj">
            <governor idx="2">has</governor>
            <dependent idx="4">opportunity</dependent>
          </dep>
          <dep type="mark">
            <governor idx="6">abolish</governor>
            <dependent idx="5">to</dependent>
          </dep>
          <dep type="acl">
            <governor idx="4">opportunity</governor>
            <dependent idx="6">abolish</dependent>
          </dep>
          <dep type="det">
            <governor idx="8">ideas</governor>
            <dependent idx="7">these</dependent>
          </dep>
          <dep type="dobj">
            <governor idx="6">abolish</governor>
            <dependent idx="8">ideas</dependent>
          </dep>
          <dep type="case">
            <governor idx="10">Earth</governor>
            <dependent idx="9">on</dependent>
          </dep>
          <dep type="nmod">
            <governor idx="8">ideas</governor>
            <dependent idx="10">Earth</dependent>
          </dep>
          <dep type="case">
            <governor idx="13">vote</governor>
            <dependent idx="11">through</dependent>
          </dep>
          <dep type="det">
            <governor idx="13">vote</governor>
            <dependent idx="12">a</dependent>
          </dep>
          <dep type="nmod">
            <governor idx="6">abolish</governor>
            <dependent idx="13">vote</dependent>
          </dep>
          <dep type="punct">
            <governor idx="2">has</governor>
            <dependent idx="14">,</dependent>
          </dep>
          <dep type="cc">
            <governor idx="2">has</governor>
            <dependent idx="15">but</dependent>
          </dep>
          <dep type="nsubj">
            <governor idx="21">working</governor>
            <dependent idx="16">organizations</dependent>
          </dep>
          <dep type="case">
            <governor idx="19">shadows</governor>
            <dependent idx="17">in</dependent>
          </dep>
          <dep type="det">
            <governor idx="19">shadows</governor>
            <dependent idx="18">the</dependent>
          </dep>
          <dep type="nmod">
            <governor idx="16">organizations</governor>
            <dependent idx="19">shadows</dependent>
          </dep>
          <dep type="aux">
            <governor idx="21">working</governor>
            <dependent idx="20">are</dependent>
          </dep>
          <dep type="conj">
            <governor idx="2">has</governor>
            <dependent idx="21">working</dependent>
          </dep>
          <dep type="mark">
            <governor idx="27">happen</governor>
            <dependent idx="22">so</dependent>
          </dep>
          <dep type="mwe">
            <governor idx="22">so</governor>
            <dependent idx="23">that</dependent>
          </dep>
          <dep type="nsubj">
            <governor idx="27">happen</governor>
            <dependent idx="24">it</dependent>
          </dep>
          <dep type="aux">
            <governor idx="27">happen</governor>
            <dependent idx="25">does</dependent>
          </dep>
          <dep type="neg">
            <governor idx="27">happen</governor>
            <dependent idx="26">n't</dependent>
          </dep>
          <dep type="advcl">
            <governor idx="21">working</governor>
            <dependent idx="27">happen</dependent>
          </dep>
          <dep type="punct">
            <governor idx="2">has</governor>
            <dependent idx="28">.</dependent>
          </dep>
        </dependencies>
        <dependencies type="collapsed-dependencies">
          <dep type="root">
            <governor idx="0">ROOT</governor>
            <dependent idx="2">has</dependent>
          </dep>
          <dep type="nsubj">
            <governor idx="2">has</governor>
            <dependent idx="1">Ross</dependent>
          </dep>
          <dep type="det">
            <governor idx="4">opportunity</governor>
            <dependent idx="3">an</dependent>
          </dep>
          <dep type="dobj">
            <governor idx="2">has</governor>
            <dependent idx="4">opportunity</dependent>
          </dep>
          <dep type="mark">
            <governor idx="6">abolish</governor>
            <dependent idx="5">to</dependent>
          </dep>
          <dep type="acl">
            <governor idx="4">opportunity</governor>
            <dependent idx="6">abolish</dependent>
          </dep>
          <dep type="det">
            <governor idx="8">ideas</governor>
            <dependent idx="7">these</dependent>
          </dep>
          <dep type="dobj">
            <governor idx="6">abolish</governor>
            <dependent idx="8">ideas</dependent>
          </dep>
          <dep type="case">
            <governor idx="10">Earth</governor>
            <dependent idx="9">on</dependent>
          </dep>
          <dep type="nmod:on">
            <governor idx="8">ideas</governor>
            <dependent idx="10">Earth</dependent>
          </dep>
          <dep type="case">
            <governor idx="13">vote</governor>
            <dependent idx="11">through</dependent>
          </dep>
          <dep type="det">
            <governor idx="13">vote</governor>
            <dependent idx="12">a</dependent>
          </dep>
          <dep type="nmod:through">
            <governor idx="6">abolish</governor>
            <dependent idx="13">vote</dependent>
          </dep>
          <dep type="punct">
            <governor idx="2">has</governor>
            <dependent idx="14">,</dependent>
          </dep>
          <dep type="cc">
            <governor idx="2">has</governor>
            <dependent idx="15">but</dependent>
          </dep>
          <dep type="nsubj">
            <governor idx="21">working</governor>
            <dependent idx="16">organizations</dependent>
          </dep>
          <dep type="case">
            <governor idx="19">shadows</governor>
            <dependent idx="17">in</dependent>
          </dep>
          <dep type="det">
            <governor idx="19">shadows</governor>
            <dependent idx="18">the</dependent>
          </dep>
          <dep type="nmod:in">
            <governor idx="16">organizations</governor>
            <dependent idx="19">shadows</dependent>
          </dep>
          <dep type="aux">
            <governor idx="21">working</governor>
            <dependent idx="20">are</dependent>
          </dep>
          <dep type="conj:but">
            <governor idx="2">has</governor>
            <dependent idx="21">working</dependent>
          </dep>
          <dep type="mark">
            <governor idx="27">happen</governor>
            <dependent idx="22">so</dependent>
          </dep>
          <dep type="mwe">
            <governor idx="22">so</governor>
            <dependent idx="23">that</dependent>
          </dep>
          <dep type="nsubj">
            <governor idx="27">happen</governor>
            <dependent idx="24">it</dependent>
          </dep>
          <dep type="aux">
            <governor idx="27">happen</governor>
            <dependent idx="25">does</dependent>
          </dep>
          <dep type="neg">
            <governor idx="27">happen</governor>
            <dependent idx="26">n't</dependent>
          </dep>
          <dep type="advcl">
            <governor idx="21">working</governor>
            <dependent idx="27">happen</dependent>
          </dep>
          <dep type="punct">
            <governor idx="2">has</governor>
            <dependent idx="28">.</dependent>
          </dep>
        </dependencies>
        <dependencies type="collapsed-ccprocessed-dependencies">
          <dep type="root">
            <governor idx="0">ROOT</governor>
            <dependent idx="2">has</dependent>
          </dep>
          <dep type="nsubj">
            <governor idx="2">has</governor>
            <dependent idx="1">Ross</dependent>
          </dep>
          <dep type="det">
            <governor idx="4">opportunity</governor>
            <dependent idx="3">an</dependent>
          </dep>
          <dep type="dobj">
            <governor idx="2">has</governor>
            <dependent idx="4">opportunity</dependent>
          </dep>
          <dep type="mark">
            <governor idx="6">abolish</governor>
            <dependent idx="5">to</dependent>
          </dep>
          <dep type="acl">
            <governor idx="4">opportunity</governor>
            <dependent idx="6">abolish</dependent>
          </dep>
          <dep type="det">
            <governor idx="8">ideas</governor>
            <dependent idx="7">these</dependent>
          </dep>
          <dep type="dobj">
            <governor idx="6">abolish</governor>
            <dependent idx="8">ideas</dependent>
          </dep>
          <dep type="case">
            <governor idx="10">Earth</governor>
            <dependent idx="9">on</dependent>
          </dep>
          <dep type="nmod:on">
            <governor idx="8">ideas</governor>
            <dependent idx="10">Earth</dependent>
          </dep>
          <dep type="case">
            <governor idx="13">vote</governor>
            <dependent idx="11">through</dependent>
          </dep>
          <dep type="det">
            <governor idx="13">vote</governor>
            <dependent idx="12">a</dependent>
          </dep>
          <dep type="nmod:through">
            <governor idx="6">abolish</governor>
            <dependent idx="13">vote</dependent>
          </dep>
          <dep type="punct">
            <governor idx="2">has</governor>
            <dependent idx="14">,</dependent>
          </dep>
          <dep type="cc">
            <governor idx="2">has</governor>
            <dependent idx="15">but</dependent>
          </dep>
          <dep type="nsubj">
            <governor idx="21">working</governor>
            <dependent idx="16">organizations</dependent>
          </dep>
          <dep type="case">
            <governor idx="19">shadows</governor>
            <dependent idx="17">in</dependent>
          </dep>
          <dep type="det">
            <governor idx="19">shadows</governor>
            <dependent idx="18">the</dependent>
          </dep>
          <dep type="nmod:in">
            <governor idx="16">organizations</governor>
            <dependent idx="19">shadows</dependent>
          </dep>
          <dep type="aux">
            <governor idx="21">working</governor>
            <dependent idx="20">are</dependent>
          </dep>
          <dep type="conj:but">
            <governor idx="2">has</governor>
            <dependent idx="21">working</dependent>
          </dep>
          <dep type="mark">
            <governor idx="27">happen</governor>
            <dependent idx="22">so</dependent>
          </dep>
          <dep type="mwe">
            <governor idx="22">so</governor>
            <dependent idx="23">that</dependent>
          </dep>
          <dep type="nsubj">
            <governor idx="27">happen</governor>
            <dependent idx="24">it</dependent>
          </dep>
          <dep type="aux">
            <governor idx="27">happen</governor>
            <dependent idx="25">does</dependent>
          </dep>
          <dep type="neg">
            <governor idx="27">happen</governor>
            <dependent idx="26">n't</dependent>
          </dep>
          <dep type="advcl">
            <governor idx="21">working</governor>
            <dependent idx="27">happen</dependent>
          </dep>
          <dep type="punct">
            <governor idx="2">has</governor>
            <dependent idx="28">.</dependent>
          </dep>
        </dependencies>
        <dependencies type="enhanced-dependencies">
          <dep type="root">
            <governor idx="0">ROOT</governor>
            <dependent idx="2">has</dependent>
          </dep>
          <dep type="nsubj">
            <governor idx="2">has</governor>
            <dependent idx="1">Ross</dependent>
          </dep>
          <dep type="det">
            <governor idx="4">opportunity</governor>
            <dependent idx="3">an</dependent>
          </dep>
          <dep type="dobj">
            <governor idx="2">has</governor>
            <dependent idx="4">opportunity</dependent>
          </dep>
          <dep type="mark">
            <governor idx="6">abolish</governor>
            <dependent idx="5">to</dependent>
          </dep>
          <dep type="acl:to">
            <governor idx="4">opportunity</governor>
            <dependent idx="6">abolish</dependent>
          </dep>
          <dep type="det">
            <governor idx="8">ideas</governor>
            <dependent idx="7">these</dependent>
          </dep>
          <dep type="dobj">
            <governor idx="6">abolish</governor>
            <dependent idx="8">ideas</dependent>
          </dep>
          <dep type="case">
            <governor idx="10">Earth</governor>
            <dependent idx="9">on</dependent>
          </dep>
          <dep type="nmod:on">
            <governor idx="8">ideas</governor>
            <dependent idx="10">Earth</dependent>
          </dep>
          <dep type="case">
            <governor idx="13">vote</governor>
            <dependent idx="11">through</dependent>
          </dep>
          <dep type="det">
            <governor idx="13">vote</governor>
            <dependent idx="12">a</dependent>
          </dep>
          <dep type="nmod:through">
            <governor idx="6">abolish</governor>
            <dependent idx="13">vote</dependent>
          </dep>
          <dep type="punct">
            <governor idx="2">has</governor>
            <dependent idx="14">,</dependent>
          </dep>
          <dep type="cc">
            <governor idx="2">has</governor>
            <dependent idx="15">but</dependent>
          </dep>
          <dep type="nsubj">
            <governor idx="21">working</governor>
            <dependent idx="16">organizations</dependent>
          </dep>
          <dep type="case">
            <governor idx="19">shadows</governor>
            <dependent idx="17">in</dependent>
          </dep>
          <dep type="det">
            <governor idx="19">shadows</governor>
            <dependent idx="18">the</dependent>
          </dep>
          <dep type="nmod:in">
            <governor idx="16">organizations</governor>
            <dependent idx="19">shadows</dependent>
          </dep>
          <dep type="aux">
            <governor idx="21">working</governor>
            <dependent idx="20">are</dependent>
          </dep>
          <dep type="conj:but">
            <governor idx="2">has</governor>
            <dependent idx="21">working</dependent>
          </dep>
          <dep type="mark">
            <governor idx="27">happen</governor>
            <dependent idx="22">so</dependent>
          </dep>
          <dep type="mwe">
            <governor idx="22">so</governor>
            <dependent idx="23">that</dependent>
          </dep>
          <dep type="nsubj">
            <governor idx="27">happen</governor>
            <dependent idx="24">it</dependent>
          </dep>
          <dep type="aux">
            <governor idx="27">happen</governor>
            <dependent idx="25">does</dependent>
          </dep>
          <dep type="neg">
            <governor idx="27">happen</governor>
            <dependent idx="26">n't</dependent>
          </dep>
          <dep type="advcl:so_that">
            <governor idx="21">working</governor>
            <dependent idx="27">happen</dependent>
          </dep>
          <dep type="punct">
            <governor idx="2">has</governor>
            <dependent idx="28">.</dependent>
          </dep>
        </dependencies>
        <dependencies type="enhanced-plus-plus-dependencies">
          <dep type="root">
            <governor idx="0">ROOT</governor>
            <dependent idx="2">has</dependent>
          </dep>
          <dep type="nsubj">
            <governor idx="2">has</governor>
            <dependent idx="1">Ross</dependent>
          </dep>
          <dep type="det">
            <governor idx="4">opportunity</governor>
            <dependent idx="3">an</dependent>
          </dep>
          <dep type="dobj">
            <governor idx="2">has</governor>
            <dependent idx="4">opportunity</dependent>
          </dep>
          <dep type="mark">
            <governor idx="6">abolish</governor>
            <dependent idx="5">to</dependent>
          </dep>
          <dep type="acl:to">
            <governor idx="4">opportunity</governor>
            <dependent idx="6">abolish</dependent>
          </dep>
          <dep type="det">
            <governor idx="8">ideas</governor>
            <dependent idx="7">these</dependent>
          </dep>
          <dep type="dobj">
            <governor idx="6">abolish</governor>
            <dependent idx="8">ideas</dependent>
          </dep>
          <dep type="case">
            <governor idx="10">Earth</governor>
            <dependent idx="9">on</dependent>
          </dep>
          <dep type="nmod:on">
            <governor idx="8">ideas</governor>
            <dependent idx="10">Earth</dependent>
          </dep>
          <dep type="case">
            <governor idx="13">vote</governor>
            <dependent idx="11">through</dependent>
          </dep>
          <dep type="det">
            <governor idx="13">vote</governor>
            <dependent idx="12">a</dependent>
          </dep>
          <dep type="nmod:through">
            <governor idx="6">abolish</governor>
            <dependent idx="13">vote</dependent>
          </dep>
          <dep type="punct">
            <governor idx="2">has</governor>
            <dependent idx="14">,</dependent>
          </dep>
          <dep type="cc">
            <governor idx="2">has</governor>
            <dependent idx="15">but</dependent>
          </dep>
          <dep type="nsubj">
            <governor idx="21">working</governor>
            <dependent idx="16">organizations</dependent>
          </dep>
          <dep type="case">
            <governor idx="19">shadows</governor>
            <dependent idx="17">in</dependent>
          </dep>
          <dep type="det">
            <governor idx="19">shadows</governor>
            <dependent idx="18">the</dependent>
          </dep>
          <dep type="nmod:in">
            <governor idx="16">organizations</governor>
            <dependent idx="19">shadows</dependent>
          </dep>
          <dep type="aux">
            <governor idx="21">working</governor>
            <dependent idx="20">are</dependent>
          </dep>
          <dep type="conj:but">
            <governor idx="2">has</governor>
            <dependent idx="21">working</dependent>
          </dep>
          <dep type="mark">
            <governor idx="27">happen</governor>
            <dependent idx="22">so</dependent>
          </dep>
          <dep type="mwe">
            <governor idx="22">so</governor>
            <dependent idx="23">that</dependent>
          </dep>
          <dep type="nsubj">
            <governor idx="27">happen</governor>
            <dependent idx="24">it</dependent>
          </dep>
          <dep type="aux">
            <governor idx="27">happen</governor>
            <dependent idx="25">does</dependent>
          </dep>
          <dep type="neg">
            <governor idx="27">happen</governor>
            <dependent idx="26">n't</dependent>
          </dep>
          <dep type="advcl:so_that">
            <governor idx="21">working</governor>
            <dependent idx="27">happen</dependent>
          </dep>
          <dep type="punct">
            <governor idx="2">has</governor>
            <dependent idx="28">.</dependent>
          </dep>
        </dependencies>
      </sentence>
      <sentence id="4">
        <tokens>
          <token id="1">
            <word>-LRB-</word>
            <lemma>-lrb-</lemma>
            <CharacterOffsetBegin>387</CharacterOffsetBegin>
            <CharacterOffsetEnd>388</CharacterOffsetEnd>
            <POS>-LRB-</POS>
            <NER>O</NER>
            <Speaker>PER0</Speaker>
          </token>
          <token id="2">
            <word>Source</word>
            <lemma>source</lemma>
            <CharacterOffsetBegin>388</CharacterOffsetBegin>
            <CharacterOffsetEnd>394</CharacterOffsetEnd>
            <POS>NN</POS>
            <NER>O</NER>
            <Speaker>PER0</Speaker>
          </token>
          <token id="3">
            <word>:</word>
            <lemma>:</lemma>
            <CharacterOffsetBegin>394</CharacterOffsetBegin>
            <CharacterOffsetEnd>395</CharacterOffsetEnd>
            <POS>:</POS>
            <NER>O</NER>
            <Speaker>PER0</Speaker>
          </token>
          <token id="4">
            <word>ANN</word>
            <lemma>ANN</lemma>
            <CharacterOffsetBegin>396</CharacterOffsetBegin>
            <CharacterOffsetEnd>399</CharacterOffsetEnd>
            <POS>NNP</POS>
            <NER>ORGANIZATION</NER>
            <Speaker>PER0</Speaker>
          </token>
          <token id="5">
            <word>-RRB-</word>
            <lemma>-rrb-</lemma>
            <CharacterOffsetBegin>399</CharacterOffsetBegin>
            <CharacterOffsetEnd>400</CharacterOffsetEnd>
            <POS>-RRB-</POS>
            <NER>O</NER>
            <Speaker>PER0</Speaker>
          </token>
        </tokens>
        <parse>(ROOT (NP (-LRB- -LRB-) (NP (NN Source)) (: :) (NP (NNP ANN)) (-RRB- -RRB-))) </parse>
        <dependencies type="basic-dependencies">
          <dep type="root">
            <governor idx="0">ROOT</governor>
            <dependent idx="2">Source</dependent>
          </dep>
          <dep type="punct">
            <governor idx="2">Source</governor>
            <dependent idx="1">-LRB-</dependent>
          </dep>
          <dep type="punct">
            <governor idx="2">Source</governor>
            <dependent idx="3">:</dependent>
          </dep>
          <dep type="dep">
            <governor idx="2">Source</governor>
            <dependent idx="4">ANN</dependent>
          </dep>
          <dep type="punct">
            <governor idx="2">Source</governor>
            <dependent idx="5">-RRB-</dependent>
          </dep>
        </dependencies>
        <dependencies type="collapsed-dependencies">
          <dep type="root">
            <governor idx="0">ROOT</governor>
            <dependent idx="2">Source</dependent>
          </dep>
          <dep type="punct">
            <governor idx="2">Source</governor>
            <dependent idx="1">-LRB-</dependent>
          </dep>
          <dep type="punct">
            <governor idx="2">Source</governor>
            <dependent idx="3">:</dependent>
          </dep>
          <dep type="dep">
            <governor idx="2">Source</governor>
            <dependent idx="4">ANN</dependent>
          </dep>
          <dep type="punct">
            <governor idx="2">Source</governor>
            <dependent idx="5">-RRB-</dependent>
          </dep>
        </dependencies>
        <dependencies type="collapsed-ccprocessed-dependencies">
          <dep type="root">
            <governor idx="0">ROOT</governor>
            <dependent idx="2">Source</dependent>
          </dep>
          <dep type="punct">
            <governor idx="2">Source</governor>
            <dependent idx="1">-LRB-</dependent>
          </dep>
          <dep type="punct">
            <governor idx="2">Source</governor>
            <dependent idx="3">:</dependent>
          </dep>
          <dep type="dep">
            <governor idx="2">Source</governor>
            <dependent idx="4">ANN</dependent>
          </dep>
          <dep type="punct">
            <governor idx="2">Source</governor>
            <dependent idx="5">-RRB-</dependent>
          </dep>
        </dependencies>
        <dependencies type="enhanced-dependencies">
          <dep type="root">
            <governor idx="0">ROOT</governor>
            <dependent idx="2">Source</dependent>
          </dep>
          <dep type="punct">
            <governor idx="2">Source</governor>
            <dependent idx="1">-LRB-</dependent>
          </dep>
          <dep type="punct">
            <governor idx="2">Source</governor>
            <dependent idx="3">:</dependent>
          </dep>
          <dep type="dep">
            <governor idx="2">Source</governor>
            <dependent idx="4">ANN</dependent>
          </dep>
          <dep type="punct">
            <governor idx="2">Source</governor>
            <dependent idx="5">-RRB-</dependent>
          </dep>
        </dependencies>
        <dependencies type="enhanced-plus-plus-dependencies">
          <dep type="root">
            <governor idx="0">ROOT</governor>
            <dependent idx="2">Source</dependent>
          </dep>
          <dep type="punct">
            <governor idx="2">Source</governor>
            <dependent idx="1">-LRB-</dependent>
          </dep>
          <dep type="punct">
            <governor idx="2">Source</governor>
            <dependent idx="3">:</dependent>
          </dep>
          <dep type="dep">
            <governor idx="2">Source</governor>
            <dependent idx="4">ANN</dependent>
          </dep>
          <dep type="punct">
            <governor idx="2">Source</governor>
            <dependent idx="5">-RRB-</dependent>
          </dep>
        </dependencies>
      </sentence>
    </sentences>
    <coreference>
      <coreference>
        <mention representative="true">
          <sentence>1</sentence>
          <start>12</start>
          <end>13</end>
          <head>12</head>
          <text>Ross</text>
        </mention>
        <mention>
          <sentence>3</sentence>
          <start>1</start>
          <end>2</end>
          <head>1</head>
          <text>Ross</text>
        </mention>
      </coreference>
      <coreference>
        <mention representative="true">
          <sentence>1</sentence>
          <start>5</start>
          <end>6</end>
          <head>5</head>
          <text>they</text>
        </mention>
        <mention>
          <sentence>2</sentence>
          <start>2</start>
          <end>3</end>
          <head>2</head>
          <text>their</text>
        </mention>
        <mention>
          <sentence>2</sentence>
          <start>6</start>
          <end>7</end>
          <head>6</head>
          <text>they</text>
        </mention>
        <mention>
          <sentence>2</sentence>
          <start>9</start>
          <end>10</end>
          <head>9</head>
          <text>their</text>
        </mention>
      </coreference>
      <coreference>
        <mention representative="true">
          <sentence>3</sentence>
          <start>3</start>
          <end>14</end>
          <head>4</head>
          <text>an opportunity to abolish these ideas on Earth through a vote</text>
        </mention>
        <mention>
          <sentence>3</sentence>
          <start>24</start>
          <end>25</end>
          <head>24</head>
          <text>it</text>
        </mention>
      </coreference>
    </coreference>
  </document>
</root>
